higher_lower/__init__.py
higher_lower-0.1.dist-info/LICENSE
higher_lower-0.1.dist-info/METADATA
higher_lower-0.1.dist-info/WHEEL
higher_lower-0.1.dist-info/top_level.txt
higher_lower-0.1.dist-info/RECORD
