Metadata-Version: 2.1
Name: higher-lower
Version: 0.1
Summary: Functions for finding numbers using higher/lower
Home-page: https://github.com/simonw/higher-lower
Author: Simon Willison
License: Apache License, Version 2.0
Project-URL: Issues, https://github.com/simonw/higher-lower/issues
Project-URL: CI, https://github.com/simonw/higher-lower/actions
Project-URL: Changelog, https://github.com/simonw/higher-lower/releases
Platform: UNKNOWN
Requires-Python: >=3.6
Provides-Extra: test
Requires-Dist: pytest ; extra == 'test'
Requires-Dist: hypothesis ; extra == 'test'
